upyt/__init__.py
upyt/connection.py
upyt/read_proxy.py
upyt/sync.py
upyt/upy_fs.py
upyt/upy_repl.py
upyt/upy_terminal.py
upyt/cli/__init__.py
upyt/cli/cat.py
upyt/cli/cp.py
upyt/cli/hybrid_filesystem_api.py
upyt/cli/interrupt.py
upyt/cli/ls.py
upyt/cli/mkdir.py
upyt/cli/reset.py
upyt/cli/rm.py
upyt/cli/sync.py
upyt/cli/terminal.py
upyt-0.0.1.dist-info/METADATA
upyt-0.0.1.dist-info/WHEEL
upyt-0.0.1.dist-info/entry_points.txt
upyt-0.0.1.dist-info/top_level.txt
upyt-0.0.1.dist-info/RECORD
