Metadata-Version: 2.1
Name: upyt
Version: 0.0.1
Requires-Dist: pyserial
